Workbook

Sheet Data
A1: Order_ID | B1: Customer_ID | C1: Order_Date | D1: Region | E1: Product_Category | F1: Customer_Segment | G1: Quantity | H1: Unit_Price | I1: Discount_Rate | J1: Revenue | K1: Cost | L1: Profit | M1: Payment_Method | N1: Discount_Bracket
A2: 1 | B2: CUST3818 | C2: 45522 | D2: North | E2: Clothing | F2: Corporate | G2: 5 | H2: 300.68 | I2: 0.27 | J2: 1097.48 | K2: 768.29 | L2: 329.19 | M2: Credit Card | N2: =_xlfn.IFS(I2=0,"No Discount",I2>=0.21,"High",I2>=0.11,"Medium",I2>=0.01,"Low") -> High
A3: 2 | B3: CUST9689 | C3: 45462 | D3: South | E3: Beauty | F3: Home Office | G3: 9 | H3: 32.89 | I3: 0.02 | J3: 290.09 | K3: 179.33 | L3: 110.76 | M3: Debit Card | N3: =_xlfn.IFS(I3=0,"No Discount",I3>=0.21,"High",I3>=0.11,"Medium",I3>=0.01,"Low") -> Low
A4: 3 | B4: CUST9147 | C4: 45617 | D4: West | E4: Sports | F4: Corporate | G4: 5 | H4: 345.61 | I4: 0.25 | J4: 1296.04 | K4: 1022.6 | L4: 273.44 | M4: Credit Card | N4: =_xlfn.IFS(I4=0,"No Discount",I4>=0.21,"High",I4>=0.11,"Medium",I4>=0.01,"Low") -> High
A5: 4 | B5: CUST7938 | C5: 45492 | D5: North | E5: Clothing | F5: Consumer | G5: 1 | H5: 444.5 | I5: 0.06 | J5: 417.83 | K5: 280.99 | L5: 136.84 | M5: UPI | N5: =_xlfn.IFS(I5=0,"No Discount",I5>=0.21,"High",I5>=0.11,"Medium",I5>=0.01,"Low") -> Low
A6: 5 | B6: CUST5127 | C6: 45593 | D6: South | E6: Home & Kitchen | F6: Consumer | G6: 5 | H6: 65.13 | I6: 0.21 | J6: 257.26 | K6: 151.9 | L6: 105.36 | M6: Credit Card | N6: =_xlfn.IFS(I6=0,"No Discount",I6>=0.21,"High",I6>=0.11,"Medium",I6>=0.01,"Low") -> High
A7: 6 | B7: CUST4834 | C7: 45587 | D7: North | E7: Sports | F7: Consumer | G7: 1 | H7: 253.38 | I7: 0.01 | J7: 250.85 | K7: 164.5 | L7: 86.35 | M7: Credit Card | N7: =_xlfn.IFS(I7=0,"No Discount",I7>=0.21,"High",I7>=0.11,"Medium",I7>=0.01,"Low") -> Low
A8: 7 | B8: CUST4649 | C8: 45413 | D8: West | E8: Electronics | F8: Home Office | G8: 8 | H8: 338.17 | I8: 0.11 | J8: 2407.77 | K8: 1564.72 | L8: 843.05 | M8: Credit Card | N8: =_xlfn.IFS(I8=0,"No Discount",I8>=0.21,"High",I8>=0.11,"Medium",I8>=0.01,"Low") -> Medium
A9: 8 | B9: CUST3844 | C9: 45515 | D9: South | E9: Clothing | F9: Corporate | G9: 9 | H9: 270.42 | I9: 0.24 | J9: 1849.67 | K9: 1413.48 | L9: 436.19 | M9: UPI | N9: =_xlfn.IFS(I9=0,"No Discount",I9>=0.21,"High",I9>=0.11,"Medium",I9>=0.01,"Low") -> High
A10: 9 | B10: CUST1425 | C10: 45424 | D10: West | E10: Electronics | F10: Corporate | G10: 9 | H10: 32.71 | I10: 0.18 | J10: 241.4 | K10: 174.37 | L10: 67.03 | M10: Credit Card | N10: =_xlfn.IFS(I10=0,"No Discount",I10>=0.21,"High",I10>=0.11,"Medium",I10>=0.01,"Low") -> Medium
A11: 10 | B11: CUST3261 | C11: 45419 | D11: South | E11: Beauty | F11: Consumer | G11: 10 | H11: 15.32 | I11: 0.18 | J11: 125.62 | K11: 67.54 | L11: 58.08 | M11: Debit Card | N11: =_xlfn.IFS(I11=0,"No Discount",I11>=0.21,"High",I11>=0.11,"Medium",I11>=0.01,"Low") -> Medium
A12: 11 | B12: CUST6670 | C12: 45573 | D12: West | E12: Electronics | F12: Home Office | G12: 3 | H12: 380.14 | I12: 0.06 | J12: 1071.99 | K12: 830.81 | L12: 241.18 | M12: Debit Card | N12: =_xlfn.IFS(I12=0,"No Discount",I12>=0.21,"High",I12>=0.11,"Medium",I12>=0.01,"Low") -> Low
A13: 12 | B13: CUST7712 | C13: 45572 | D13: East | E13: Sports | F13: Consumer | G13: 8 | H13: 47.52 | I13: 0.28 | J13: 273.72 | K13: 139.74 | L13: 133.98 | M13: Net Banking | N13: =_xlfn.IFS(I13=0,"No Discount",I13>=0.21,"High",I13>=0.11,"Medium",I13>=0.01,"Low") -> High
... A10001: 10000 | B10001: CUST8377 | C10001: 45455 | D10001: North | E10001: Electronics | F10001: Consumer | G10001: 8 | H10001: 423.22 | I10001: 0.3 | J10001: 2370.03 | K10001: 1831.04 | L10001: 538.99 | M10001: Net Banking | N10001: =_xlfn.IFS(I10001=0,"No Discount",I10001>=0.21,"High",I10001>=0.11,"Medium",I10001>=0.01,"Low") -> High

Sheet Discount Impact Analysis 
A1: Discount_Bracket | B1: Total Revenue | C1: Total Profit | D1: Profit Margin
A2: No Discount | B2: =SUMIF(Data!N2:N10001,'Discount Impact Analysis '!A2,Data!J2:J10001) -> 233892.56 | C2: =SUMIF(Data!N2:N10001,'Discount Impact Analysis '!A2,Data!L2:L10001) -> 83341.16 | D2: =C2/B2 -> 0.35632241
A3: Low | B3: =SUMIF(Data!N3:N10002,'Discount Impact Analysis '!A3,Data!J3:J10002) -> 4405576.4 | C3: =SUMIF(Data!N3:N10002,'Discount Impact Analysis '!A3,Data!L3:L10002) -> 1540860.6 | D3: =C3/B3 -> 0.34975232
A4: Medium | B4: =SUMIF(Data!N4:N10003,'Discount Impact Analysis '!A4,Data!J4:J10003) -> 3964345.5 | C4: =SUMIF(Data!N4:N10003,'Discount Impact Analysis '!A4,Data!L4:L10003) -> 1383747.4 | D4: =C4/B4 -> 0.34904814
A5: High | B5: =SUMIF(Data!N5:N10004,'Discount Impact Analysis '!A5,Data!J5:J10004) -> 3346211.5 | C5: =SUMIF(Data!N5:N10004,'Discount Impact Analysis '!A5,Data!L5:L10004) -> 1180945.9 | D5: =C5/B5 -> 0.35292028
A7: Region | B7: Total Revenue | C7: Total Profit | D7: Profit Margin | E7: Avg Discount Rate
A8: North | B8: =SUMIF(Data!D2:D10001,'Discount Impact Analysis '!A8,Data!J2:J10001) -> 3038232.2 | C8: =SUMIF(Data!D2:D10001,'Discount Impact Analysis '!A8,Data!L2:L10001) -> 1068527.7 | D8: =C8/B8 -> 0.3516939 | E8: =AVERAGEIF(Data!D2:D10001,'Discount Impact Analysis '!A8,Data!I2:I10001) -> 0.15096546
A9: South | B9: =SUMIF(Data!D3:D10002,'Discount Impact Analysis '!A9,Data!J3:J10002) -> 2942636 | C9: =SUMIF(Data!D3:D10002,'Discount Impact Analysis '!A9,Data!L3:L10002) -> 1030989.4 | D9: =C9/B9 -> 0.35036254 | E9: =AVERAGEIF(Data!D3:D10002,'Discount Impact Analysis '!A9,Data!I3:I10002) -> 0.15108943
A10: East | B10: =SUMIF(Data!D4:D10003,'Discount Impact Analysis '!A10,Data!J4:J10003) -> 2987841.7 | C10: =SUMIF(Data!D4:D10003,'Discount Impact Analysis '!A10,Data!L4:L10003) -> 1049453 | D10: =C10/B10 -> 0.35124117 | E10: =AVERAGEIF(Data!D4:D10003,'Discount Impact Analysis '!A10,Data!I4:I10003) -> 0.15137271
A11: West | B11: =SUMIF(Data!D5:D10004,'Discount Impact Analysis '!A11,Data!J5:J10004) -> 2982413.6 | C11: =SUMIF(Data!D5:D10004,'Discount Impact Analysis '!A11,Data!L5:L10004) -> 1040254.1 | D11: =C11/B11 -> 0.34879605 | E11: =AVERAGEIF(Data!D5:D10004,'Discount Impact Analysis '!A11,Data!I5:I10004) -> 0.14760161
A13: Product_Category | B13: Total Revenue | C13: Total Profit | D13: Profit Margin | E13: Avg Discount Rate
A14: Clothing | B14: =SUMIF(Data!E2:E10001,'Discount Impact Analysis '!A14,Data!J2:J10001) -> 2333518.1 | C14: =SUMIF(Data!E2:E10001,'Discount Impact Analysis '!A14,Data!L2:L10001) -> 815424.41 | D14: =C14/B14 -> 0.34943993 | E14: =AVERAGEIF(Data!E2:E10001,'Discount Impact Analysis '!A14,Data!I2:I10001) -> 0.14803785
A15: Beauty | B15: =SUMIF(Data!E3:E10002,'Discount Impact Analysis '!A15,Data!J3:J10002) -> 2427867.2 | C15: =SUMIF(Data!E3:E10002,'Discount Impact Analysis '!A15,Data!L3:L10002) -> 845766.25 | D15: =C15/B15 -> 0.34835771 | E15: =AVERAGEIF(Data!E3:E10002,'Discount Impact Analysis '!A15,Data!I3:I10002) -> 0.15098697
A16: Sports | B16: =SUMIF(Data!E4:E10003,'Discount Impact Analysis '!A16,Data!J4:J10003) -> 2380619.7 | C16: =SUMIF(Data!E4:E10003,'Discount Impact Analysis '!A16,Data!L4:L10003) -> 831067.45 | D16: =C16/B16 -> 0.3490971 | E16: =AVERAGEIF(Data!E4:E10003,'Discount Impact Analysis '!A16,Data!I4:I10003) -> 0.15142714
A17: Home & Kitchen | B17: =SUMIF(Data!E5:E10004,'Discount Impact Analysis '!A17,Data!J5:J10004) -> 2377096.1 | C17: =SUMIF(Data!E5:E10004,'Discount Impact Analysis '!A17,Data!L5:L10004) -> 843057.02 | D17: =C17/B17 -> 0.35465837 | E17: =AVERAGEIF(Data!E5:E10004,'Discount Impact Analysis '!A17,Data!I5:I10004) -> 0.15166833
A18: Electronics | B18: =SUMIF(Data!E6:E10005,'Discount Impact Analysis '!A18,Data!J6:J10005) -> 2433318.4 | C18: =SUMIF(Data!E6:E10005,'Discount Impact Analysis '!A18,Data!L6:L10005) -> 854182.55 | D18: =C18/B18 -> 0.35103608 | E18: =AVERAGEIF(Data!E6:E10005,'Discount Impact Analysis '!A18,Data!I6:I10005) -> 0.14924159
A20: KEY FINDINGS:
A21: 1. Profit margin konsisten di 35% di semua level discount, menunjukkan strategi pricing yang terkontrol
A22: 2. Low discount (1-10%) menghasilkan revenue tertinggi (4.4jt) — discount kecil sudah cukup mendorong penjualan
A23: 3. Semua region menerapkan kebijakan discount seragam di rata-rata 15%
A24: 4. Tidak ada kategori produk yang mendominasi dalam pemberian discount
A26: BUSINESS RECOMMENDATION:
A27: 1. Pertahankan strategi discount di level Low (1-10%) karena terbukti menghasilkan revenue tertinggi
A28: 2. Evaluasi transaksi No Discount — volume sangat kecil, perlu strategi untuk meningkatkan transaksi tanpa discount
A29: 3. Standarisasi kebijakan discount di semua region sudah berjalan baik, pertahankan

Sheet V Discount Impact Analysis 
D1: Analysis Summary Discount Impact Analysis

Sheet Customer Segmentation
A1: Customer_Segment | B1: Total Revenue | C1: Total Profit | D1: Profit Margin | E1: Total Transactions
A2: Consumer | B2: =SUMIF(Data!F2:F10001,'Customer Segmentation'!A2,Data!J2:J10001) -> 3978433.1 | C2: =SUMIF(Data!F2:F10001,'Customer Segmentation'!A2,Data!L2:L10001) -> 1392831.2 | D2: =C2/B2 -> 0.35009542 | E2: =COUNTIF(Data!F2:F10001,'Customer Segmentation'!A2) -> 3295
A3: Corporate | B3: =SUMIF(Data!F3:F10002,'Customer Segmentation'!A3,Data!J3:J10002) -> 3993829.8 | C3: =SUMIF(Data!F3:F10002,'Customer Segmentation'!A3,Data!L3:L10002) -> 1400131 | D3: =C3/B3 -> 0.35057354 | E3: =COUNTIF(Data!F3:F10002,'Customer Segmentation'!A3) -> 3315
A4: Home Office | B4: =SUMIF(Data!F4:F10003,'Customer Segmentation'!A4,Data!J4:J10003) -> 3978769 | C4: =SUMIF(Data!F4:F10003,'Customer Segmentation'!A4,Data!L4:L10003) -> 1396095.5 | D4: =C4/B4 -> 0.35088629 | E4: =COUNTIF(Data!F4:F10003,'Customer Segmentation'!A4) -> 3388
A7: Customer_Segment | B7: Avg Order Value | C7: Avg Quantity | D7: Avg Unit Price
A8: Consumer | B8: =AVERAGEIF(Data!F2:F10001,'Customer Segmentation'!A8,Data!J2:J10001) -> 1207.4152 | C8: =AVERAGEIF(Data!F2:F10001,'Customer Segmentation'!A8,Data!G2:G10001) -> 5.5435508 | D8: =AVERAGEIF(Data!F2:F10001,'Customer Segmentation'!A8,Data!H2:H10001) -> 257.57622
A9: Corporate | B9: =AVERAGEIF(Data!F3:F10002,'Customer Segmentation'!A9,Data!J3:J10002) -> 1204.7752 | C9: =AVERAGEIF(Data!F3:F10002,'Customer Segmentation'!A9,Data!G3:G10002) -> 5.5662142 | D9: =AVERAGEIF(Data!F3:F10002,'Customer Segmentation'!A9,Data!H3:H10002) -> 256.13216
A10: Home Office | B10: =AVERAGEIF(Data!F4:F10003,'Customer Segmentation'!A10,Data!J4:J10003) -> 1174.371 | C10: =AVERAGEIF(Data!F4:F10003,'Customer Segmentation'!A10,Data!G4:G10003) -> 5.4341795 | D10: =AVERAGEIF(Data!F4:F10003,'Customer Segmentation'!A10,Data!H4:H10003) -> 252.93001
A12: Customer_Segment | B12: Credit Card | C12: Debit Card | D12: UPI | E12: Net Banking | F12: Cash on Delivery | G12: Most Preferred
A13: Consumer | B13: =COUNTIFS(Data!F2:F10001,'Customer Segmentation'!A13,Data!M2:M10001,'Customer Segmentation'!B12) -> 664 | C13: =COUNTIFS(Data!F2:F10001,'Customer Segmentation'!A13,Data!M2:M10001,C12) -> 661 | D13: =COUNTIFS(Data!F2:F10001,'Customer Segmentation'!A13,Data!M2:M10001,D12) -> 685 | E13: =COUNTIFS(Data!F2:F10001,'Customer Segmentation'!A13,Data!M2:M10001,E12) -> 633 | F13: =COUNTIFS(Data!F2:F10001,'Customer Segmentation'!A13,Data!M2:M10001,F12) -> 652 | G13: =INDEX(B12:F12,MATCH(MAX(B13:F13),B13:F13,0)) -> UPI
A14: Corporate | B14: =COUNTIFS(Data!F2:F10001,'Customer Segmentation'!A14,Data!M2:M10001,'Customer Segmentation'!B12) -> 649 | C14: =COUNTIFS(Data!F2:F10001,'Customer Segmentation'!A14,Data!M2:M10001,C12) -> 686 | D14: =COUNTIFS(Data!F2:F10001,'Customer Segmentation'!A14,Data!M2:M10001,D12) -> 670 | E14: =COUNTIFS(Data!F2:F10001,'Customer Segmentation'!A14,Data!M2:M10001,E12) -> 635 | F14: =COUNTIFS(Data!F2:F10001,'Customer Segmentation'!A14,Data!M2:M10001,F12) -> 676 | G14: =INDEX(B12:F12,MATCH(MAX(B14:F14),B14:F14,0)) -> Debit Card
A15: Home Office | B15: =COUNTIFS(Data!F2:F10001,'Customer Segmentation'!A15,Data!M2:M10001,'Customer Segmentation'!B12) -> 650 | C15: =COUNTIFS(Data!F2:F10001,'Customer Segmentation'!A15,Data!M2:M10001,C12) -> 727 | D15: =COUNTIFS(Data!F2:F10001,'Customer Segmentation'!A15,Data!M2:M10001,D12) -> 656 | E15: =COUNTIFS(Data!F2:F10001,'Customer Segmentation'!A15,Data!M2:M10001,E12) -> 667 | F15: =COUNTIFS(Data!F2:F10001,'Customer Segmentation'!A15,Data!M2:M10001,F12) -> 689 | G15: =INDEX(B12:F12,MATCH(MAX(B15:F15),B15:F15,0)) -> Debit Card
A17: KEY FINDINGS:
A18: 1. Ketiga segment memiliki profit margin yang sama di 35% dengan distribusi revenue yang merata
A19: 2. Consumer memiliki Avg Order Value tertinggi (1207) — cenderung belanja lebih besar per transaksi
A20: 3. Home Office memiliki transaksi terbanyak (3388) namun Avg Order Value terendah (1174)
A21: 4. Consumer lebih suka UPI, sedangkan Corporate dan Home Office lebih suka Debit Card
A22: 5. Corporate + Electronics menghasilkan kombinasi profit tertinggi (304rb)
A24: BUSINESS RECOMMENDATION:
A25: 1. Fokuskan promosi produk Electronics ke segment Corporate karena menghasilkan profit tertinggi
A26: 2. Tingkatkan nilai transaksi segment Home Office dengan strategi bundling atau upselling
A27: 3. Optimalkan payment gateway UPI untuk segment Consumer dan Debit Card untuk Corporate & Home Office

Sheet Profitability Analysis 
A1: Product_Category | B1: Total Revenue | C1: Total Cost | D1: Total Profit | E1: Profit Margin
A2: Clothing | B2: =SUMIF(Data!E2:E10001,'Profitability Analysis '!A2,Data!J2:J10001) -> 2333518.1 | C2: =SUMIF(Data!E2:E10001,'Profitability Analysis '!A2,Data!K2:K10001) -> 1518093.7 | D2: =SUMIF(Data!E2:E10001,'Profitability Analysis '!A2,Data!L2:L10001) -> 815424.41 | E2: =D2/B2 -> 0.34943993
A3: Beauty | B3: =SUMIF(Data!E3:E10002,'Profitability Analysis '!A3,Data!J3:J10002) -> 2427867.2 | C3: =SUMIF(Data!E3:E10002,'Profitability Analysis '!A3,Data!K3:K10002) -> 1582100.9 | D3: =SUMIF(Data!E3:E10002,'Profitability Analysis '!A3,Data!L3:L10002) -> 845766.25 | E3: =D3/B3 -> 0.34835771
A4: Sports | B4: =SUMIF(Data!E4:E10003,'Profitability Analysis '!A4,Data!J4:J10003) -> 2380619.7 | C4: =SUMIF(Data!E4:E10003,'Profitability Analysis '!A4,Data!K4:K10003) -> 1549552.3 | D4: =SUMIF(Data!E4:E10003,'Profitability Analysis '!A4,Data!L4:L10003) -> 831067.45 | E4: =D4/B4 -> 0.3490971
A5: Home & Kitchen | B5: =SUMIF(Data!E5:E10004,'Profitability Analysis '!A5,Data!J5:J10004) -> 2377096.1 | C5: =SUMIF(Data!E5:E10004,'Profitability Analysis '!A5,Data!K5:K10004) -> 1534039.1 | D5: =SUMIF(Data!E5:E10004,'Profitability Analysis '!A5,Data!L5:L10004) -> 843057.02 | E5: =D5/B5 -> 0.35465837
A6: Electronics | B6: =SUMIF(Data!E6:E10005,'Profitability Analysis '!A6,Data!J6:J10005) -> 2433318.4 | C6: =SUMIF(Data!E6:E10005,'Profitability Analysis '!A6,Data!K6:K10005) -> 1579135.8 | D6: =SUMIF(Data!E6:E10005,'Profitability Analysis '!A6,Data!L6:L10005) -> 854182.55 | E6: =D6/B6 -> 0.35103608
A8: Product_Category | B8: Profit Margin | C8: Cost Ratio | D8: Revenue per Transaction
A9: Clothing | B9: =D2/B2 -> 0.34943993 | C9: =C2/B2 -> 0.65056007 | D9: =AVERAGEIF(Data!E2:E10001,'Profitability Analysis '!A9,Data!J2:J10001) -> 1162.1106
A10: Beauty | B10: =D3/B3 -> 0.34835771 | C10: =C3/B3 -> 0.65164229 | D10: =AVERAGEIF(Data!E3:E10002,'Profitability Analysis '!A10,Data!J3:J10002) -> 1216.3663
A11: Sports | B11: =D4/B4 -> 0.3490971 | C11: =C4/B4 -> 0.6509029 | D11: =AVERAGEIF(Data!E4:E10003,'Profitability Analysis '!A11,Data!J4:J10003) -> 1192.098
A12: Home & Kitchen | B12: =D5/B5 -> 0.35465837 | C12: =C5/B5 -> 0.64534163 | D12: =AVERAGEIF(Data!E5:E10004,'Profitability Analysis '!A12,Data!J5:J10004) -> 1183.8128
A13: Electronics | B13: =D6/B6 -> 0.35103608 | C13: =C6/B6 -> 0.64896392 | D13: =AVERAGEIF(Data!E6:E10005,'Profitability Analysis '!A13,Data!J6:J10005) -> 1222.1589
A15: Product_Category | B15: Consumer | C15: Corporate | D15: Home Office
A16: Clothing | B16: =SUMIFS(Data!L2:L10001,Data!E2:E10001,'Profitability Analysis '!A16,Data!F2:F10001,'Profitability Analysis '!B15) -> 273926.21 | C16: =SUMIFS(Data!L2:L10001,Data!E2:E10001,'Profitability Analysis '!A16,Data!F2:F10001,'Profitability Analysis '!C15) -> 276304.35 | D16: =SUMIFS(Data!L2:L10001,Data!E2:E10001,'Profitability Analysis '!A16,Data!F2:F10001,'Profitability Analysis '!D15) -> 265193.85
A17: Beauty | B17: =SUMIFS(Data!L2:L10001,Data!E2:E10001,'Profitability Analysis '!A17,Data!F2:F10001,'Profitability Analysis '!B15) -> 296015.57 | C17: =SUMIFS(Data!L2:L10001,Data!E2:E10001,'Profitability Analysis '!A17,Data!F2:F10001,'Profitability Analysis '!C15) -> 268046.02 | D17: =SUMIFS(Data!L2:L10001,Data!E2:E10001,'Profitability Analysis '!A17,Data!F2:F10001,'Profitability Analysis '!D15) -> 281704.66
A18: Sports | B18: =SUMIFS(Data!L2:L10001,Data!E2:E10001,'Profitability Analysis '!A18,Data!F2:F10001,'Profitability Analysis '!B15) -> 287372.68 | C18: =SUMIFS(Data!L2:L10001,Data!E2:E10001,'Profitability Analysis '!A18,Data!F2:F10001,'Profitability Analysis '!C15) -> 268521.44 | D18: =SUMIFS(Data!L2:L10001,Data!E2:E10001,'Profitability Analysis '!A18,Data!F2:F10001,'Profitability Analysis '!D15) -> 275173.33
A19: Home & Kitchen | B19: =SUMIFS(Data!L2:L10001,Data!E2:E10001,'Profitability Analysis '!A19,Data!F2:F10001,'Profitability Analysis '!B15) -> 268001.14 | C19: =SUMIFS(Data!L2:L10001,Data!E2:E10001,'Profitability Analysis '!A19,Data!F2:F10001,'Profitability Analysis '!C15) -> 283447.26 | D19: =SUMIFS(Data!L2:L10001,Data!E2:E10001,'Profitability Analysis '!A19,Data!F2:F10001,'Profitability Analysis '!D15) -> 291608.62
A20: Electronics | B20: =SUMIFS(Data!L2:L10001,Data!E2:E10001,'Profitability Analysis '!A20,Data!F2:F10001,'Profitability Analysis '!B15) -> 267515.62 | C20: =SUMIFS(Data!L2:L10001,Data!E2:E10001,'Profitability Analysis '!A20,Data!F2:F10001,'Profitability Analysis '!C15) -> 304141.14 | D20: =SUMIFS(Data!L2:L10001,Data!E2:E10001,'Profitability Analysis '!A20,Data!F2:F10001,'Profitability Analysis '!D15) -> 282525.79
A22: KEY FINDINGS:
A23: 1. Semua kategori produk memiliki profit margin konsisten di 35%
A24: 2. Electronics menghasilkan Total Revenue dan Total Profit tertinggi (2.43jt & 854rb)
A25: 3. Home & Kitchen memiliki Cost Ratio terendah (64.5%) — paling efisien dari sisi biaya
A26: 4. Electronics memiliki Revenue per Transaction tertinggi (1222) — pembeli cenderung belanja paling besar
A27: 5. Corporate + Electronics menghasilkan profit tertinggi di semua kombinasi category + segment (304rb)
A29: BUSINESS RECOMMENDATION:
A30: 1. Prioritaskan investasi di kategori Electronics karena menghasilkan revenue dan profit tertinggi
A31: 2. Pertahankan efisiensi biaya di Home & Kitchen yang sudah terbukti memiliki Cost Ratio terendah
A32: 3. Tingkatkan strategi penjualan Clothing karena memiliki Revenue per Transaction terendah (1162)

Sheet RFM Tabel
A1: Customer ID | B1: Last_Purchase | C1: Frequency | D1: Monetary
A2: CUST1000 | B2: 45651 | C2: 2 | D2: 739.18
A3: CUST1003 | B3: 45511 | C3: 2 | D3: 3215.94
A4: CUST1004 | B4: 45599 | C4: 1 | D4: 3279.23
A5: CUST1005 | B5: 45432 | C5: 1 | D5: 83.51
A6: CUST1006 | B6: 45327 | C6: 1 | D6: 885.71
A7: CUST1008 | B7: 45583 | C7: 1 | D7: 361.75
A8: CUST1010 | B8: 45595 | C8: 5 | D8: 6031.86
A9: CUST1011 | B9: 45362 | C9: 1 | D9: 1563.9
A10: CUST1012 | B10: 45492 | C10: 2 | D10: 1234.41
A11: CUST1013 | B11: 45307 | C11: 1 | D11: 729.04
A12: CUST1015 | B12: 45601 | C12: 2 | D12: 2904.17
A13: CUST1016 | B13: 45294 | C13: 1 | D13: 529.31
... A5996: Grand Total | B5996: 45657 | C5996: 10000 | D5996: 11952419

Sheet RFM Analysis
A1: Customer ID | B1: Last_Purchase | C1: Frequency | D1: Monetary | E1: Recency | F1: F2 (R_Score) | G1: G2 (F_Score) | H1: H2 (M_Score) | I1: RFM_Score | J1: Customer_Category | M1: Customer_Category | N1: Total Customers | O1: % of Total | P1: Avg Monetary | Q1: Avg Frequency
A2: CUST1000 | B2: 45651 | C2: 2 | D2: 739.18 | E2: =TODAY()-B2 -> 428 | F2: =_xlfn.IFS(E2<100,3,E2<=200,2,E2>200,1) -> 1 | G2: =_xlfn.IFS(C2>=3,3,C2=2,2,C2=1,1) -> 2 | H2: =_xlfn.IFS(D2>=2000,3,D2>=1000,2,D2<1000,1) -> 1 | I2: =F2+G2+H2 -> 4 | J2: =_xlfn.IFS(I2>=7,"Champion",I2>=5,"Loyal",I2>=4,"At Risk",I2<4,"Lost") -> At Risk | M2: Champion | N2: =COUNTIF(J2:J5995,M2) -> 788 | O2: =N2/5994 -> 0.1314648 | P2: =AVERAGEIF(J2:J5995,M2,D2:D5995) -> 4422.3877 | Q2: =AVERAGEIF(J2:J5995,M2,C2:C5995) -> 3.3692893
A3: CUST1003 | B3: 45511 | C3: 2 | D3: 3215.94 | E3: =TODAY()-B3 -> 568 | F3: =_xlfn.IFS(E3<100,3,E3<=200,2,E3>200,1) -> 1 | G3: =_xlfn.IFS(C3>=3,3,C3=2,2,C3=1,1) -> 2 | H3: =_xlfn.IFS(D3>=2000,3,D3>=1000,2,D3<1000,1) -> 3 | I3: =F3+G3+H3 -> 6 | J3: =_xlfn.IFS(I3>=7,"Champion",I3>=5,"Loyal",I3>=4,"At Risk",I3<4,"Lost") -> Loyal | M3: Loyal | N3: =COUNTIF(J3:J5996,M3) -> 2316 | O3: =N3/5994 -> 0.38638639 | P3: =AVERAGEIF(J3:J5996,M3,D3:D5996) -> 2672.9507 | Q3: =AVERAGEIF(J3:J5996,M3,C3:C5996) -> 1.791019
A4: CUST1004 | B4: 45599 | C4: 1 | D4: 3279.23 | E4: =TODAY()-B4 -> 480 | F4: =_xlfn.IFS(E4<100,3,E4<=200,2,E4>200,1) -> 1 | G4: =_xlfn.IFS(C4>=3,3,C4=2,2,C4=1,1) -> 1 | H4: =_xlfn.IFS(D4>=2000,3,D4>=1000,2,D4<1000,1) -> 3 | I4: =F4+G4+H4 -> 5 | J4: =_xlfn.IFS(I4>=7,"Champion",I4>=5,"Loyal",I4>=4,"At Risk",I4<4,"Lost") -> Loyal | M4: At Risk | N4: =COUNTIF(J4:J5997,M4) -> 1206 | O4: =N4/5994 -> 0.2012012 | P4: =AVERAGEIF(J4:J5997,M4,D4:D5997) -> 1246.2393 | Q4: =AVERAGEIF(J4:J5997,M4,C4:C5997) -> 1.2537313
A5: CUST1005 | B5: 45432 | C5: 1 | D5: 83.51 | E5: =TODAY()-B5 -> 647 | F5: =_xlfn.IFS(E5<100,3,E5<=200,2,E5>200,1) -> 1 | G5: =_xlfn.IFS(C5>=3,3,C5=2,2,C5=1,1) -> 1 | H5: =_xlfn.IFS(D5>=2000,3,D5>=1000,2,D5<1000,1) -> 1 | I5: =F5+G5+H5 -> 3 | J5: =_xlfn.IFS(I5>=7,"Champion",I5>=5,"Loyal",I5>=4,"At Risk",I5<4,"Lost") -> Lost | M5: Lost | N5: =COUNTIF(J5:J5998,M5) -> 1683 | O5: =N5/5994 -> 0.28078078 | P5: =AVERAGEIF(J5:J5998,M5,D5:D5998) -> 459.48919 | Q5: =AVERAGEIF(J5:J5998,M5,C5:C5998) -> 1
A6: CUST1006 | B6: 45327 | C6: 1 | D6: 885.71 | E6: =TODAY()-B6 -> 752 | F6: =_xlfn.IFS(E6<100,3,E6<=200,2,E6>200,1) -> 1 | G6: =_xlfn.IFS(C6>=3,3,C6=2,2,C6=1,1) -> 1 | H6: =_xlfn.IFS(D6>=2000,3,D6>=1000,2,D6<1000,1) -> 1 | I6: =F6+G6+H6 -> 3 | J6: =_xlfn.IFS(I6>=7,"Champion",I6>=5,"Loyal",I6>=4,"At Risk",I6<4,"Lost") -> Lost
A7: CUST1008 | B7: 45583 | C7: 1 | D7: 361.75 | E7: =TODAY()-B7 -> 496 | F7: =_xlfn.IFS(E7<100,3,E7<=200,2,E7>200,1) -> 1 | G7: =_xlfn.IFS(C7>=3,3,C7=2,2,C7=1,1) -> 1 | H7: =_xlfn.IFS(D7>=2000,3,D7>=1000,2,D7<1000,1) -> 1 | I7: =F7+G7+H7 -> 3 | J7: =_xlfn.IFS(I7>=7,"Champion",I7>=5,"Loyal",I7>=4,"At Risk",I7<4,"Lost") -> Lost | M7: KEY FINDINGS:
A8: CUST1010 | B8: 45595 | C8: 5 | D8: 6031.86 | E8: =TODAY()-B8 -> 484 | F8: =_xlfn.IFS(E8<100,3,E8<=200,2,E8>200,1) -> 1 | G8: =_xlfn.IFS(C8>=3,3,C8=2,2,C8=1,1) -> 3 | H8: =_xlfn.IFS(D8>=2000,3,D8>=1000,2,D8<1000,1) -> 3 | I8: =F8+G8+H8 -> 7 | J8: =_xlfn.IFS(I8>=7,"Champion",I8>=5,"Loyal",I8>=4,"At Risk",I8<4,"Lost") -> Champion | M8: 1. Hanya 13% customer (788) masuk kategori Champion — frequent buyer dengan avg belanja 4422
A9: CUST1011 | B9: 45362 | C9: 1 | D9: 1563.9 | E9: =TODAY()-B9 -> 717 | F9: =_xlfn.IFS(E9<100,3,E9<=200,2,E9>200,1) -> 1 | G9: =_xlfn.IFS(C9>=3,3,C9=2,2,C9=1,1) -> 1 | H9: =_xlfn.IFS(D9>=2000,3,D9>=1000,2,D9<1000,1) -> 2 | I9: =F9+G9+H9 -> 4 | J9: =_xlfn.IFS(I9>=7,"Champion",I9>=5,"Loyal",I9>=4,"At Risk",I9<4,"Lost") -> At Risk | M9: 2. Loyal customer adalah segment terbesar (39%) dengan potensi naik ke Champion
A10: CUST1012 | B10: 45492 | C10: 2 | D10: 1234.41 | E10: =TODAY()-B10 -> 587 | F10: =_xlfn.IFS(E10<100,3,E10<=200,2,E10>200,1) -> 1 | G10: =_xlfn.IFS(C10>=3,3,C10=2,2,C10=1,1) -> 2 | H10: =_xlfn.IFS(D10>=2000,3,D10>=1000,2,D10<1000,1) -> 2 | I10: =F10+G10+H10 -> 5 | J10: =_xlfn.IFS(I10>=7,"Champion",I10>=5,"Loyal",I10>=4,"At Risk",I10<4,"Lost") -> Loyal | M10: 3. 28% customer (1683) berstatus Lost — hanya bertransaksi 1 kali dan tidak kembali
A11: CUST1013 | B11: 45307 | C11: 1 | D11: 729.04 | E11: =TODAY()-B11 -> 772 | F11: =_xlfn.IFS(E11<100,3,E11<=200,2,E11>200,1) -> 1 | G11: =_xlfn.IFS(C11>=3,3,C11=2,2,C11=1,1) -> 1 | H11: =_xlfn.IFS(D11>=2000,3,D11>=1000,2,D11<1000,1) -> 1 | I11: =F11+G11+H11 -> 3 | J11: =_xlfn.IFS(I11>=7,"Champion",I11>=5,"Loyal",I11>=4,"At Risk",I11<4,"Lost") -> Lost | M11: 4. Terdapat perbedaan signifikan Avg Monetary antara Champion (4422) dan Lost (459) — selisih hampir 10x
A12: CUST1015 | B12: 45601 | C12: 2 | D12: 2904.17 | E12: =TODAY()-B12 -> 478 | F12: =_xlfn.IFS(E12<100,3,E12<=200,2,E12>200,1) -> 1 | G12: =_xlfn.IFS(C12>=3,3,C12=2,2,C12=1,1) -> 2 | H12: =_xlfn.IFS(D12>=2000,3,D12>=1000,2,D12<1000,1) -> 3 | I12: =F12+G12+H12 -> 6 | J12: =_xlfn.IFS(I12>=7,"Champion",I12>=5,"Loyal",I12>=4,"At Risk",I12<4,"Lost") -> Loyal | M12: 5. At Risk customer (20%) masih bisa diselamatkan sebelum menjadi Lost
A13: CUST1016 | B13: 45294 | C13: 1 | D13: 529.31 | E13: =TODAY()-B13 -> 785 | F13: =_xlfn.IFS(E13<100,3,E13<=200,2,E13>200,1) -> 1 | G13: =_xlfn.IFS(C13>=3,3,C13=2,2,C13=1,1) -> 1 | H13: =_xlfn.IFS(D13>=2000,3,D13>=1000,2,D13<1000,1) -> 1 | I13: =F13+G13+H13 -> 3 | J13: =_xlfn.IFS(I13>=7,"Champion",I13>=5,"Loyal",I13>=4,"At Risk",I13<4,"Lost") -> Lost
A14: CUST1017 | B14: 45305 | C14: 2 | D14: 1374.44 | E14: =TODAY()-B14 -> 774 | F14: =_xlfn.IFS(E14<100,3,E14<=200,2,E14>200,1) -> 1 | G14: =_xlfn.IFS(C14>=3,3,C14=2,2,C14=1,1) -> 2 | H14: =_xlfn.IFS(D14>=2000,3,D14>=1000,2,D14<1000,1) -> 2 | I14: =F14+G14+H14 -> 5 | J14: =_xlfn.IFS(I14>=7,"Champion",I14>=5,"Loyal",I14>=4,"At Risk",I14<4,"Lost") -> Loyal | M14: BUSINESS RECOMMENDATION:
A15: CUST1018 | B15: 45413 | C15: 2 | D15: 3133.21 | E15: =TODAY()-B15 -> 666 | F15: =_xlfn.IFS(E15<100,3,E15<=200,2,E15>200,1) -> 1 | G15: =_xlfn.IFS(C15>=3,3,C15=2,2,C15=1,1) -> 2 | H15: =_xlfn.IFS(D15>=2000,3,D15>=1000,2,D15<1000,1) -> 3 | I15: =F15+G15+H15 -> 6 | J15: =_xlfn.IFS(I15>=7,"Champion",I15>=5,"Loyal",I15>=4,"At Risk",I15<4,"Lost") -> Loyal | M15: 1. Berikan program loyalitas eksklusif untuk Champion agar tetap aktif dan tidak churn
A16: CUST1019 | B16: 45431 | C16: 2 | D16: 1962.84 | E16: =TODAY()-B16 -> 648 | F16: =_xlfn.IFS(E16<100,3,E16<=200,2,E16>200,1) -> 1 | G16: =_xlfn.IFS(C16>=3,3,C16=2,2,C16=1,1) -> 2 | H16: =_xlfn.IFS(D16>=2000,3,D16>=1000,2,D16<1000,1) -> 2 | I16: =F16+G16+H16 -> 5 | J16: =_xlfn.IFS(I16>=7,"Champion",I16>=5,"Loyal",I16>=4,"At Risk",I16<4,"Lost") -> Loyal | M16: 2. Fokuskan strategi upselling ke segment Loyal untuk mendorong mereka naik ke Champion
A17: CUST1025 | B17: 45481 | C17: 1 | D17: 825.3 | E17: =TODAY()-B17 -> 598 | F17: =_xlfn.IFS(E17<100,3,E17<=200,2,E17>200,1) -> 1 | G17: =_xlfn.IFS(C17>=3,3,C17=2,2,C17=1,1) -> 1 | H17: =_xlfn.IFS(D17>=2000,3,D17>=1000,2,D17<1000,1) -> 1 | I17: =F17+G17+H17 -> 3 | J17: =_xlfn.IFS(I17>=7,"Champion",I17>=5,"Loyal",I17>=4,"At Risk",I17<4,"Lost") -> Lost | M17: 3. Jalankan re-engagement campaign untuk At Risk — berikan promo atau reminder sebelum terlambat
A18: CUST1026 | B18: 45317 | C18: 1 | D18: 1340.06 | E18: =TODAY()-B18 -> 762 | F18: =_xlfn.IFS(E18<100,3,E18<=200,2,E18>200,1) -> 1 | G18: =_xlfn.IFS(C18>=3,3,C18=2,2,C18=1,1) -> 1 | H18: =_xlfn.IFS(D18>=2000,3,D18>=1000,2,D18<1000,1) -> 2 | I18: =F18+G18+H18 -> 4 | J18: =_xlfn.IFS(I18>=7,"Champion",I18>=5,"Loyal",I18>=4,"At Risk",I18<4,"Lost") -> At Risk | M18: 4. Investigasi penyebab Lost customer hanya bertransaksi 1 kali — apakah ada masalah di pengalaman belanja?
A19: CUST1027 | B19: 45649 | C19: 1 | D19: 577.51 | E19: =TODAY()-B19 -> 430 | F19: =_xlfn.IFS(E19<100,3,E19<=200,2,E19>200,1) -> 1 | G19: =_xlfn.IFS(C19>=3,3,C19=2,2,C19=1,1) -> 1 | H19: =_xlfn.IFS(D19>=2000,3,D19>=1000,2,D19<1000,1) -> 1 | I19: =F19+G19+H19 -> 3 | J19: =_xlfn.IFS(I19>=7,"Champion",I19>=5,"Loyal",I19>=4,"At Risk",I19<4,"Lost") -> Lost
A20: CUST1031 | B20: 45450 | C20: 1 | D20: 324.81 | E20: =TODAY()-B20 -> 629 | F20: =_xlfn.IFS(E20<100,3,E20<=200,2,E20>200,1) -> 1 | G20: =_xlfn.IFS(C20>=3,3,C20=2,2,C20=1,1) -> 1 | H20: =_xlfn.IFS(D20>=2000,3,D20>=1000,2,D20<1000,1) -> 1 | I20: =F20+G20+H20 -> 3 | J20: =_xlfn.IFS(I20>=7,"Champion",I20>=5,"Loyal",I20>=4,"At Risk",I20<4,"Lost") -> Lost
A21: CUST1032 | B21: 45504 | C21: 1 | D21: 3874.81 | E21: =TODAY()-B21 -> 575 | F21: =_xlfn.IFS(E21<100,3,E21<=200,2,E21>200,1) -> 1 | G21: =_xlfn.IFS(C21>=3,3,C21=2,2,C21=1,1) -> 1 | H21: =_xlfn.IFS(D21>=2000,3,D21>=1000,2,D21<1000,1) -> 3 | I21: =F21+G21+H21 -> 5 | J21: =_xlfn.IFS(I21>=7,"Champion",I21>=5,"Loyal",I21>=4,"At Risk",I21<4,"Lost") -> Loyal
A22: CUST1035 | B22: 45558 | C22: 1 | D22: 353.62 | E22: =TODAY()-B22 -> 521 | F22: =_xlfn.IFS(E22<100,3,E22<=200,2,E22>200,1) -> 1 | G22: =_xlfn.IFS(C22>=3,3,C22=2,2,C22=1,1) -> 1 | H22: =_xlfn.IFS(D22>=2000,3,D22>=1000,2,D22<1000,1) -> 1 | I22: =F22+G22+H22 -> 3 | J22: =_xlfn.IFS(I22>=7,"Champion",I22>=5,"Loyal",I22>=4,"At Risk",I22<4,"Lost") -> Lost
A23: CUST1036 | B23: 45657 | C23: 2 | D23: 4913.78 | E23: =TODAY()-B23 -> 422 | F23: =_xlfn.IFS(E23<100,3,E23<=200,2,E23>200,1) -> 1 | G23: =_xlfn.IFS(C23>=3,3,C23=2,2,C23=1,1) -> 2 | H23: =_xlfn.IFS(D23>=2000,3,D23>=1000,2,D23<1000,1) -> 3 | I23: =F23+G23+H23 -> 6 | J23: =_xlfn.IFS(I23>=7,"Champion",I23>=5,"Loyal",I23>=4,"At Risk",I23<4,"Lost") -> Loyal
A24: CUST1038 | B24: 45588 | C24: 1 | D24: 3089.94 | E24: =TODAY()-B24 -> 491 | F24: =_xlfn.IFS(E24<100,3,E24<=200,2,E24>200,1) -> 1 | G24: =_xlfn.IFS(C24>=3,3,C24=2,2,C24=1,1) -> 1 | H24: =_xlfn.IFS(D24>=2000,3,D24>=1000,2,D24<1000,1) -> 3 | I24: =F24+G24+H24 -> 5 | J24: =_xlfn.IFS(I24>=7,"Champion",I24>=5,"Loyal",I24>=4,"At Risk",I24<4,"Lost") -> Loyal
A25: CUST1040 | B25: 45320 | C25: 1 | D25: 829.21 | E25: =TODAY()-B25 -> 759 | F25: =_xlfn.IFS(E25<100,3,E25<=200,2,E25>200,1) -> 1 | G25: =_xlfn.IFS(C25>=3,3,C25=2,2,C25=1,1) -> 1 | H25: =_xlfn.IFS(D25>=2000,3,D25>=1000,2,D25<1000,1) -> 1 | I25: =F25+G25+H25 -> 3 | J25: =_xlfn.IFS(I25>=7,"Champion",I25>=5,"Loyal",I25>=4,"At Risk",I25<4,"Lost") -> Lost
A26: CUST1043 | B26: 45613 | C26: 2 | D26: 3826.58 | E26: =TODAY()-B26 -> 466 | F26: =_xlfn.IFS(E26<100,3,E26<=200,2,E26>200,1) -> 1 | G26: =_xlfn.IFS(C26>=3,3,C26=2,2,C26=1,1) -> 2 | H26: =_xlfn.IFS(D26>=2000,3,D26>=1000,2,D26<1000,1) -> 3 | I26: =F26+G26+H26 -> 6 | J26: =_xlfn.IFS(I26>=7,"Champion",I26>=5,"Loyal",I26>=4,"At Risk",I26<4,"Lost") -> Loyal
A27: CUST1044 | B27: 45447 | C27: 2 | D27: 3540.93 | E27: =TODAY()-B27 -> 632 | F27: =_xlfn.IFS(E27<100,3,E27<=200,2,E27>200,1) -> 1 | G27: =_xlfn.IFS(C27>=3,3,C27=2,2,C27=1,1) -> 2 | H27: =_xlfn.IFS(D27>=2000,3,D27>=1000,2,D27<1000,1) -> 3 | I27: =F27+G27+H27 -> 6 | J27: =_xlfn.IFS(I27>=7,"Champion",I27>=5,"Loyal",I27>=4,"At Risk",I27<4,"Lost") -> Loyal
A28: CUST1048 | B28: 45518 | C28: 1 | D28: 2120.34 | E28: =TODAY()-B28 -> 561 | F28: =_xlfn.IFS(E28<100,3,E28<=200,2,E28>200,1) -> 1 | G28: =_xlfn.IFS(C28>=3,3,C28=2,2,C28=1,1) -> 1 | H28: =_xlfn.IFS(D28>=2000,3,D28>=1000,2,D28<1000,1) -> 3 | I28: =F28+G28+H28 -> 5 | J28: =_xlfn.IFS(I28>=7,"Champion",I28>=5,"Loyal",I28>=4,"At Risk",I28<4,"Lost") -> Loyal
A29: CUST1049 | B29: 45553 | C29: 1 | D29: 448.42 | E29: =TODAY()-B29 -> 526 | F29: =_xlfn.IFS(E29<100,3,E29<=200,2,E29>200,1) -> 1 | G29: =_xlfn.IFS(C29>=3,3,C29=2,2,C29=1,1) -> 1 | H29: =_xlfn.IFS(D29>=2000,3,D29>=1000,2,D29<1000,1) -> 1 | I29: =F29+G29+H29 -> 3 | J29: =_xlfn.IFS(I29>=7,"Champion",I29>=5,"Loyal",I29>=4,"At Risk",I29<4,"Lost") -> Lost
A30: CUST1050 | B30: 45580 | C30: 3 | D30: 3336.76 | E30: =TODAY()-B30 -> 499 | F30: =_xlfn.IFS(E30<100,3,E30<=200,2,E30>200,1) -> 1 | G30: =_xlfn.IFS(C30>=3,3,C30=2,2,C30=1,1) -> 3 | H30: =_xlfn.IFS(D30>=2000,3,D30>=1000,2,D30<1000,1) -> 3 | I30: =F30+G30+H30 -> 7 | J30: =_xlfn.IFS(I30>=7,"Champion",I30>=5,"Loyal",I30>=4,"At Risk",I30<4,"Lost") -> Champion
... A5995: CUST9999 | B5995: 45608 | C5995: 1 | D5995: 392.39 | E5995: =TODAY()-B5995 -> 471 | F5995: =_xlfn.IFS(E5995<100,3,E5995<=200,2,E5995>200,1) -> 1 | G5995: =_xlfn.IFS(C5995>=3,3,C5995=2,2,C5995=1,1) -> 1 | H5995: =_xlfn.IFS(D5995>=2000,3,D5995>=1000,2,D5995<1000,1) -> 1 | I5995: =F5995+G5995+H5995 -> 3 | J5995: =_xlfn.IFS(I5995>=7,"Champion",I5995>=5,"Loyal",I5995>=4,"At Risk",I5995<4,"Lost") -> Lost
